setup.py
lesson_utils/__init__.py
lesson_utils/input_utils.py
lesson_utils.egg-info/PKG-INFO
lesson_utils.egg-info/SOURCES.txt
lesson_utils.egg-info/dependency_links.txt
lesson_utils.egg-info/top_level.txt