Metadata-Version: 1.0
Name: lesson-utils
Version: 1.0.0
Summary: Collection of useful features for the course Python.
Home-page: https://github.com/kyzima-spb/lesson-utils
Author: Kirill Vercetti
Author-email: office@kyzima-spb.com
License: Apache License 2.0
Platform: UNKNOWN
